eic_aichat_models
test
